INSTALL.rst
LICENSE
MANIFEST.in
README.rst
pyproject.toml
setup.cfg
setup.py
versioneer.py
bin/nemo
bin/nemoCatalogCheck
bin/nemoMask
bin/nemoMass
bin/nemoMock
bin/nemoModel
bin/nemoSpec
docs/Makefile
docs/advanced.rst
docs/commands.rst
docs/conf.py
docs/config.rst
docs/development.rst
docs/dr3_tutorial.rst
docs/dr5_tutorial.rst
docs/dr6_tutorial.rst
docs/index.rst
docs/install.rst
docs/outputs.rst
docs/quickstart.rst
docs/reference.rst
docs/sosims_tutorial.rst
docs/testing.rst
docs/tutorials.rst
examples/ACT-DR3-clusters/ACTPol_clusters.fits
examples/ACT-DR3-clusters/ACTPol_redshifts.fits
examples/ACT-DR3-clusters/E-D56Clusters.fits
examples/ACT-DR3-clusters/README.rst
examples/ACT-DR3-clusters/equD56.yml
examples/ACT-DR3-clusters/equD56_quick.yml
examples/ACT-DR3-clusters/pointSourceMask.fits.gz
examples/ACT-DR3-clusters/selFnExample.py
examples/ACT-DR3-clusters/surveyMask.fits.gz
examples/ACT-DR3-clusters/profiles_ACT/profile_AR1_2009_pixwin_130224.txt
examples/ACT-DR5-clusters/DR5ClusterSearch.slurm
examples/ACT-DR5-clusters/DR5ClusterSearch.yml
examples/ACT-DR5-clusters/FETCH_MAPS.sh
examples/ACT-DR5-clusters/README.rst
examples/ACT-DR6-clusters/DR6ClusterSearch-S.pbs
examples/ACT-DR6-clusters/DR6ClusterSearch.pbs
examples/ACT-DR6-clusters/DR6ClusterSearch.yml
examples/ACT-DR6-clusters/FETCH_MAPS.sh
examples/ACT-DR6-clusters/README.rst
examples/SOSims/HEALPIX_TO_CAR.sh
examples/SOSims/MAKE_BEAMS.sh
examples/SOSims/MAKE_MOCKS_SMALL.sh
examples/SOSims/MAKE_MOCKS_TILES.sh
examples/SOSims/MFMF_SOSim_3freq_small.yml
examples/SOSims/MFMF_SOSim_3freq_tiles.yml
examples/SOSims/NzCheck.py
examples/SOSims/README.rst
examples/SOSims/cobayaConf_SOSims_fixedScalingRelation.yml
examples/SOSims/combineComponentMaps.py
examples/SOSims/createSurveyMask.py
examples/SOSims/healpix2CAR.py
examples/SOSims/makeGaussianBeam.py
examples/SOSims/makeRedshiftsCatalog.py
examples/SOSims/readWebSkyInputCatalog.py
examples/SOSims/selFnExample.py
examples/SOSims/slurm_cosmo.sh
nemo_sz.egg-info/PKG-INFO
nemo_sz.egg-info/SOURCES.txt
nemo_sz.egg-info/dependency_links.txt
nemo_sz.egg-info/requires.txt
nemo_sz.egg-info/top_level.txt
