Metadata-Version: 2.2
Name: nemo-sz
Version: 0.9.0
Summary: Millimeter-wave galaxy cluster and source detection package
Home-page: https://nemo-sz.readthedocs.io
Author: Matt Hilton + Nemo Contributors
Author-email: matt.hilton@wits.ac.za
License: BSD 3-Clause
Keywords: astrophysics
Classifier: Programming Language :: Python :: 3
Classifier: Environment :: Console
Classifier: Intended Audience :: Science/Research
Classifier: License :: OSI Approved :: BSD License
Classifier: Natural Language :: English
Classifier: Operating System :: POSIX
Classifier: Topic :: Scientific/Engineering :: Astronomy
License-File: LICENSE
Requires-Dist: astropy>=6.0
Requires-Dist: numpy>=2
Requires-Dist: matplotlib>=3.10
Requires-Dist: astLib>=0.13.1
Requires-Dist: pixell>=0.29
Requires-Dist: scipy>=1.10
Requires-Dist: pillow
Requires-Dist: PyYAML
Requires-Dist: pyccl>=3.0
Requires-Dist: colorcet>=1.0
Requires-Dist: mahotas>=1.4
Dynamic: author
Dynamic: author-email
Dynamic: home-page
